tests/__init__.py
tests/test_gen_gitreview.py
tests/test_genericargs.py
tests/test_hash.py
tests/test_rpmutils.py
tests/test_strutil.py
tests/test_yaml.py
toolchest/__init__.py
toolchest/decor.py
toolchest/genericargs.py
toolchest/hash.py
toolchest/introspect.py
toolchest/strutil.py
toolchest/yaml.py
toolchest/filesystem/__init__.py
toolchest/filesystem/git.py
toolchest/logging/__init__.py
toolchest/logging/logger.py
toolchest/logging/drivers/__init__.py
toolchest/logging/drivers/default.py
toolchest/rpm/__init__.py
toolchest/rpm/rpmvercmp.py
toolchest/rpm/utils.py
toolchest/validator/__init__.py
toolchest/validator/base.py
toolchest/validator/simple.py
toolchest-0.0.13.dist-info/LICENSE
toolchest-0.0.13.dist-info/METADATA
toolchest-0.0.13.dist-info/WHEEL
toolchest-0.0.13.dist-info/top_level.txt
toolchest-0.0.13.dist-info/RECORD
